{
    "nodes": [
        {"id": 1, "name": "L'Hexaler", "kind": "singer"},
        {"id": 2, "name": "El Gaouli", "kind": "singer"},
        {"id": 3, "name": "Demi Portion", "kind": "singer"},
        {"id": 4, "name": "Youssef Swatt's", "kind": "singer"},
        {"id": 5, "name": "Scylla", "kind": "singer"},
        {"id": 6, "name": "Davodka", "kind": "singer"},
        {"id": 7, "name": "Sprinter", "kind": "singer"},
        {"id": 8, "name": "Jeff le nerf", "kind": "singer"},
        {"id": 9, "name": "Swift Guad", "kind": "singer"},
        {"id": 10, "name": "Flynt", "kind": "singer"},
        {"id": 11, "name": "Guizmo", "kind": "singer"},
        {"id": 12, "name": "Furax Barbarossa", "kind": "singer"},
        {"id": 13, "name": "Lacraps", "kind": "singer"},
        {"id": 14, "name": "Saké", "kind": "singer"},
        {"id": 15, "name": "Crown", "kind": "singer"},
        {"id": 16, "name": "Melan", "kind": "singer"}
    ],
    "links": [
        {"source": 2, "target": 1, "label": "collaborated with", "year": 2015},
        {"source": 3, "target": 1, "label": "collaborated with", "year": 2016},
        {"source": 4, "target": 1, "label": "collaborated with", "year": 2017},
        {"source": 1, "target": 3, "label": "collaborated with", "year": 2016},
        {"source": 5, "target": 3, "label": "collaborated with", "year": 2018},
        {"source": 6, "target": 3, "label": "collaborated with", "year": 2019},
        {"source": 7, "target": 3, "label": "collaborated with", "year": 2020},
        {"source": 8, "target": 3, "label": "collaborated with", "year": 2021},
        {"source": 9, "target": 3, "label": "collaborated with", "year": 2022},
        {"source": 6, "target": 1, "label": "collaborated with", "year": 2019},
        {"source": 8, "target": 1, "label": "collaborated with", "year": 2021},
        {"source": 12, "target": 8, "label": "collaborated with", "year": 2020},
        {"source": 6, "target": 13, "label": "collaborated with", "year": 2021},
        {"source": 12, "target": 5, "label": "collaborated with", "year": 2018},
        {"source": 14, "target": 5, "label": "collaborated with", "year": 2017},
        {"source": 5, "target": 14, "label": "collaborated with", "year": 2017},
        {"source": 14, "target": 15, "label": "collaborated with", "year": 2022},
        {"source": 1, "target": 5, "label": "collaborated with", "year": 2016},
        {"source": 1, "target": 12, "label": "collaborated with", "year": 2018},
        {"source": 9, "target": 1, "label": "collaborated with", "year": 2020},
        {"source": 9, "target": 5, "label": "collaborated with", "year": 2021},
        {"source": 9, "target": 12, "label": "collaborated with", "year": 2022},
        {"source": 6, "target": 9, "label": "collaborated with", "year": 2021},
        {"source": 15, "target": 10, "label": "collaborated with", "year": 2019},
        {"source": 15, "target": 11, "label": "collaborated with", "year": 2020},
        {"source": 14, "target": 12, "label": "collaborated with", "year": 2021},
        {"source": 15, "target": 5, "label": "collaborated with", "year": 2022},
        {"source": 13, "target": 8, "label": "collaborated with", "year": 2020},
        {"source": 13, "target": 16, "label": "collaborated with", "year": 2021},
        {"source": 13, "target": 1, "label": "collaborated with", "year": 2019},
        {"source": 16, "target": 1, "label": "collaborated with", "year": 2020},
        {"source": 16, "target": 12, "label": "collaborated with", "year": 2021},
        {"source": 2, "target": 4, "label": "collaborated with", "year": 2018},
        {"source": 15, "target": 16, "label": "collaborated with", "year": 2022},
        {"source": 11, "target": 14, "label": "collaborated with", "year": 2020}
    ]
}